{
  "WINDOW_WIDTH": 540,
  "WINDOW_HEIGHT": 960,
  "FPS": 60,
  "ROUND_SECONDS": 180,
  "PLAYER_RADIUS": 18,
  "PLAYER_BASE_SPEED": 320,
  "GRAVITY": 900,
  "BLOCK_SIZE": 40,
  "SPAWN_ROWS_AHEAD": 40,
  "BLOCK_HP": 3,
  "COMMAND_COOLDOWN_SECONDS": 8,
  "QUEUE_POP_INTERVAL_SECONDS": 2,
  "SPONSOR_SKILL_INTERVAL_SECONDS": 25,
  "BOOST_DURATION_SECONDS": 4,
  "SLOW_DURATION_SECONDS": 4,
  "BIG_DURATION_SECONDS": 5,
  "SHIELD_DURATION_SECONDS": 6,
  "TNT_RADIUS": 110,
  "AUTO_MODE": true,
  "BLOCK_CONTACT_COOLDOWN_SECONDS": 0.085,
  "HAZARD_INVULN_SECONDS": 0.85,
  "IMPACT_HITSTOP_MAX_SECONDS": 0.05,
  "RESTITUTION_NORMAL": 0.18,
  "RESTITUTION_HAZARD": 0.05,
  "PICKAXE_SCALE": 1.6,
  "TOP_CLEAR_ROWS": 2,
  "AUTO_FALL_MUL": 0.55,
  "GRAVITY_MUL": 0.022,
  "PLAYER_START_FALL_SPEED": 130
}
